{
  "gender": "Female",
  "SeniorCitizen": "0",
  "Partner": "Yes",
  "Dependents": "Yes",
  "tenure": 18,
  "PhoneService": "Yes",
  "MultipleLines": "Yes",
  "InternetService": "Fiber optic",
  "OnlineSecurity": "Yes",
  "OnlineBackup": "Yes",
  "DeviceProtection": "Yes",
  "TechSupport": "Yes",
  "StreamingTV": "Yes",
  "StreamingMovies": "Yes",
  "Contract": "Month-to-month",
  "PaperlessBilling": "Yes",
  "PaymentMethod": "Electronic check",
  "MonthlyCharges": "185",
  "TotalCharges": "1850",
  "monthlycharges": 0,
  "totalcharges": 0,
  "submitted_at": "2026-02-13T16:10:00.760503"
}